main.py
basion_uv_demo-0.1.1.dist-info/METADATA
basion_uv_demo-0.1.1.dist-info/WHEEL
basion_uv_demo-0.1.1.dist-info/entry_points.txt
basion_uv_demo-0.1.1.dist-info/top_level.txt
basion_uv_demo-0.1.1.dist-info/RECORD
