Metadata-Version: 2.4
Name: basion-uv-demo
Version: 0.1.1
Summary: Add your description here
Requires-Python: >=3.12
Requires-Dist: numpy>=2.2.4
Requires-Dist: requests>=2.32.3
